README.md
setup.py
craygraph/__init__.py
craygraph.egg-info/PKG-INFO
craygraph.egg-info/SOURCES.txt
craygraph.egg-info/dependency_links.txt
craygraph.egg-info/requires.txt
craygraph.egg-info/top_level.txt
craygraph/graph/__init__.py
craygraph/graph/achain.py
craygraph/graph/language.py
craygraph/graph/selector.py
craygraph/meta/__init__.py
craygraph/meta/clazz.py
craygraph/meta/func.py
craygraph/meta/meta.py
craygraph/visualize/__init__.py
craygraph/visualize/viz.py