Metadata-Version: 2.1
Name: craygraph
Version: 0.2.1
Summary: A small toolkit for building dataflow-based framework.
Home-page: https://gitlab.com/craynn/craygraph
Author: Maxim Borisyak and contributors.
Author-email: maximus.been@gmail.com
Maintainer: Maxim Borisyak
Maintainer-email: maximus.been@gmail.com
License: MIT
Platform: UNKNOWN
Classifier: Development Status :: 4 - Beta
Classifier: Intended Audience :: Science/Research
Classifier: License :: OSI Approved :: MIT License
Classifier: Programming Language :: Python :: 3
Requires-Python: >=3.7
Provides-Extra: test
